LijieLinuxJincheng/README.md
LijieLinuxJincheng/__init__.py
LijieLinuxJincheng/__main__.py
LijieLinuxJincheng/file.epub
LijieLinuxJincheng/index.html
LijieLinuxJincheng/css/__init__.py
LijieLinuxJincheng/css/annotations.css
LijieLinuxJincheng/css/main.css
LijieLinuxJincheng/css/normalize.css
LijieLinuxJincheng/css/popup.css
LijieLinuxJincheng/font/__init__.py
LijieLinuxJincheng/font/fontello.eot
LijieLinuxJincheng/font/fontello.svg
LijieLinuxJincheng/font/fontello.ttf
LijieLinuxJincheng/font/fontello.woff
LijieLinuxJincheng/img/__init__.py
LijieLinuxJincheng/img/annotator-glyph-sprite.png
LijieLinuxJincheng/img/annotator-icon-sprite.png
LijieLinuxJincheng/img/apple-touch-icon.png
LijieLinuxJincheng/img/cancelfullscreen.png
LijieLinuxJincheng/img/close.png
LijieLinuxJincheng/img/fullscreen.png
LijieLinuxJincheng/img/loader.gif
LijieLinuxJincheng/img/menu-icon.png
LijieLinuxJincheng/img/save.png
LijieLinuxJincheng/img/saved.png
LijieLinuxJincheng/img/settings-s.png
LijieLinuxJincheng/img/settings.png
LijieLinuxJincheng/img/star.png
LijieLinuxJincheng/js/__init__.py
LijieLinuxJincheng/js/epub.js
LijieLinuxJincheng/js/epub.min.js
LijieLinuxJincheng/js/epub.min.map
LijieLinuxJincheng/js/hooks.min.js
LijieLinuxJincheng/js/hooks.min.map
LijieLinuxJincheng/js/reader.js
LijieLinuxJincheng/js/reader.js.map
LijieLinuxJincheng/js/reader.min.js
LijieLinuxJincheng/js/reader.min.map
LijieLinuxJincheng/js/hooks/__init__.py
LijieLinuxJincheng/js/hooks/extensions/__init__.py
LijieLinuxJincheng/js/hooks/extensions/highlight.js
LijieLinuxJincheng/js/libs/__init__.py
LijieLinuxJincheng/js/libs/jquery.min.js
LijieLinuxJincheng/js/libs/localforage.min.js
LijieLinuxJincheng/js/libs/screenfull.js
LijieLinuxJincheng/js/libs/screenfull.min.js
LijieLinuxJincheng/js/libs/zip.min.js
LijieLinuxJincheng/js/plugins/__init__.py
LijieLinuxJincheng/js/plugins/hypothesis.js
LijieLinuxJincheng/js/plugins/search.js
lijie_linux_jincheng-2024.3.2.0.dist-info/METADATA
lijie_linux_jincheng-2024.3.2.0.dist-info/WHEEL
lijie_linux_jincheng-2024.3.2.0.dist-info/entry_points.txt
lijie_linux_jincheng-2024.3.2.0.dist-info/top_level.txt
lijie_linux_jincheng-2024.3.2.0.dist-info/RECORD
